minnt/__init__.py
minnt/callback.py
minnt/format_logdir_impl.py
minnt/initializers_override.py
minnt/logger.py
minnt/loss.py
minnt/metric.py
minnt/progress_logger.py
minnt/startup_impl.py
minnt/trainable_module.py
minnt/transformed_dataset.py
minnt/type_aliases.py
minnt/utils.py
minnt/version.py
minnt/vocabulary.py
minnt/callbacks/__init__.py
minnt/callbacks/keep_best_weights.py
minnt/callbacks/save_best_weights.py
minnt/callbacks/save_weights.py
minnt/loggers/__init__.py
minnt/loggers/base_logger.py
minnt/loggers/filesystem_logger.py
minnt/loggers/multi_logger.py
minnt/loggers/tensorboard_logger.py
minnt/loggers/wandb_logger.py
minnt/losses/__init__.py
minnt/losses/binary_cross_entropy.py
minnt/losses/categorical_cross_entropy.py
minnt/losses/mean_squared_error.py
minnt/metrics/__init__.py
minnt/metrics/binary_accuracy.py
minnt/metrics/binary_cross_entropy.py
minnt/metrics/categorical_accuracy.py
minnt/metrics/categorical_cross_entropy.py
minnt/metrics/exact_match.py
minnt/metrics/mean.py
minnt/metrics/mean_squared_error.py
minnt/optimizers/__init__.py
minnt/optimizers/adafactor.py
minnt/optimizers/lazy_adam.py
minnt/optimizers/multi_optimizer.py
minnt/schedulers/__init__.py
minnt/schedulers/cosine_decay.py
minnt/schedulers/generic_decay.py
minnt/schedulers/linear_decay.py
minnt/schedulers/no_decay.py
minnt-1.0.1.dist-info/licenses/LICENSE
minnt-1.0.1.dist-info/METADATA
minnt-1.0.1.dist-info/WHEEL
minnt-1.0.1.dist-info/top_level.txt
minnt-1.0.1.dist-info/RECORD
