Metadata-Version: 2.4
Name: minnt
Version: 1.0.1
Summary: Minimalistic Neural Network Trainer
Author-email: Milan Straka <milan@strakovi.com>
License-Expression: MPL-2.0
Project-URL: Homepage, https://minnt.org
Project-URL: Repository, https://github.com/ufal/minnt
Classifier: Development Status :: 4 - Beta
Classifier: Intended Audience :: Developers
Classifier: Intended Audience :: Education
Classifier: Intended Audience :: Science/Research
Classifier: Programming Language :: Python :: 3
Classifier: Topic :: Scientific/Engineering :: Artificial Intelligence
Classifier: Topic :: Scientific/Engineering
Requires-Python: >=3.11
License-File: LICENSE
Requires-Dist: tensorboard>=2.20.0
Requires-Dist: tqdm>=4.66.0
Provides-Extra: torch
Requires-Dist: torch; extra == "torch"
Requires-Dist: torchvision; extra == "torch"
Dynamic: license-file
